nubby/__init__.py
nubby/controllers.py
nubby/injectors.py
nubby/loaders.py
nubby/models.py
nubby/builtins/__init__.py
nubby/builtins/loaders/__init__.py
nubby/builtins/loaders/json.py
nubby/builtins/loaders/toml.py
nubby/builtins/loaders/yaml.py
nubby-0.1.2.dist-info/licenses/LICENSE
nubby-0.1.2.dist-info/METADATA
nubby-0.1.2.dist-info/WHEEL
nubby-0.1.2.dist-info/top_level.txt
nubby-0.1.2.dist-info/RECORD
