Metadata-Version: 2.4
Name: nubby
Version: 0.1.2
Summary: A simple config loader for Python using Bevy for dependency injection.
Author-email: Zech Zimmerman <hi@zech.codes>
Requires-Python: >=3.12
License-File: LICENSE
Requires-Dist: bevy==3.0.0b2
Requires-Dist: tramp>=2025.3.2
Provides-Extra: yaml
Requires-Dist: pyyaml>=6.0.2; extra == "yaml"
Provides-Extra: toml
Requires-Dist: tomlkit>=0.13.2; extra == "toml"
Dynamic: license-file
